when/__init__.py
when/__main__.py
when/cli.py
when/config.py
when/core.py
when/exceptions.py
when/lunar.py
when/timezones.py
when/utils.py
when/db/__init__.py
when/db/client.py
when/db/make.py
when-3.3.2.dist-info/licenses/LICENSE
when-3.3.2.dist-info/METADATA
when-3.3.2.dist-info/WHEEL
when-3.3.2.dist-info/entry_points.txt
when-3.3.2.dist-info/top_level.txt
when-3.3.2.dist-info/RECORD
