Metadata-Version: 2.4
Name: when
Version: 3.3.2
Summary: Calculate and convert times across time zones and cities of significant population
Author-email: David Krauth <dakrauth@gmail.com>
License-Expression: MIT
Project-URL: Homepage, https://github.com/dakrauth/when
Keywords: time,timezone,timezones
Classifier: Environment :: Console
Classifier: Intended Audience :: Developers
Classifier: Operating System :: POSIX
Classifier: Operating System :: Unix
Classifier: Operating System :: MacOS :: MacOS X
Classifier: Programming Language :: Python
Classifier: Programming Language :: Python :: 3
Classifier: Programming Language :: Python :: 3.10
Classifier: Programming Language :: Python :: 3.11
Classifier: Programming Language :: Python :: 3.12
Classifier: Programming Language :: Python :: 3.13
Classifier: Programming Language :: Python :: 3.14
Classifier: Topic :: Software Development
Classifier: Topic :: Software Development :: Libraries
Classifier: Topic :: Software Development :: Libraries :: Python Modules
Classifier: Topic :: System :: Software Distribution
Classifier: Topic :: Utilities
Requires-Python: >=3.10
License-File: LICENSE
Requires-Dist: python-dateutil>=2.8.0
Requires-Dist: toml>=0.10.2
Requires-Dist: requests
Requires-Dist: fullmoon
Dynamic: license-file
